.gitignore
.travis.yml
Makefile
README.rst
REVERSE_ENGINEERING.rst
requirements-dev.txt
rocket-r60v
setup.py
Rocket_R60V.egg-info/PKG-INFO
Rocket_R60V.egg-info/SOURCES.txt
Rocket_R60V.egg-info/dependency_links.txt
Rocket_R60V.egg-info/requires.txt
Rocket_R60V.egg-info/top_level.txt
rocket_r60v/__init__.py
rocket_r60v/api.py
rocket_r60v/cli.py
rocket_r60v/exceptions.py
rocket_r60v/machine.py
rocket_r60v/message.py
rocket_r60v/settings/__init__.py
rocket_r60v/settings/base.py
rocket_r60v/settings/brew_boiler.py
rocket_r60v/settings/count.py
rocket_r60v/settings/date_time.py
rocket_r60v/settings/display.py
rocket_r60v/settings/language.py
rocket_r60v/settings/profiles.py
rocket_r60v/settings/service_boiler.py
rocket_r60v/settings/standby.py
rocket_r60v/settings/temperature_unit.py
rocket_r60v/settings/timer.py
rocket_r60v/settings/water_feed.py
rocket_r60v/tests/__init__.py
rocket_r60v/tests/machine.py
rocket_r60v/tests/message.py
rocket_r60v/tests/settings/__init__.py
rocket_r60v/tests/settings/base.py
rocket_r60v/tests/settings/brew_boiler.py
rocket_r60v/tests/settings/count.py
rocket_r60v/tests/settings/date_time.py
rocket_r60v/tests/settings/display.py
rocket_r60v/tests/settings/language.py
rocket_r60v/tests/settings/profiles.py
rocket_r60v/tests/settings/service_boiler.py
rocket_r60v/tests/settings/standby.py
rocket_r60v/tests/settings/temperature_unit.py
rocket_r60v/tests/settings/timer.py
rocket_r60v/tests/settings/water_feed.py