Metadata-Version: 2.1
Name: Rocket-R60V
Version: 1.2.1
Summary: Python API for the Rocket R 60V
Home-page: https://github.com/confirm/Rocket-R60V
Author: confirm IT solutions
License: MIT
Platform: UNKNOWN
Classifier: Programming Language :: Python :: 3
Classifier: License :: OSI Approved :: MIT License
Classifier: Operating System :: OS Independent
Requires-Python: >=3.7
Provides-Extra: develop
